hello.py
svlearn_pdf_helpers-0.1.1.dist-info/METADATA
svlearn_pdf_helpers-0.1.1.dist-info/WHEEL
svlearn_pdf_helpers-0.1.1.dist-info/top_level.txt
svlearn_pdf_helpers-0.1.1.dist-info/RECORD
