Metadata-Version: 2.1
Name: svlearn-pdf-helpers
Version: 0.1.1
Summary: Some helper functions we need while handling pdf for SupportVectors
Requires-Python: >=3.12
Requires-Dist: markdown>=3.7
Requires-Dist: pdf2image>=1.17.0
Requires-Dist: poppler-utils>=0.1.0
Requires-Dist: pypdf2>=3.0.1
Requires-Dist: weasyprint>=63.1
